kfserving/__init__.py
kfserving/api_client.py
kfserving/configuration.py
kfserving/exceptions.py
kfserving/kfmodel.py
kfserving/kfmodel_repository.py
kfserving/kfserver.py
kfserving/rest.py
kfserving/storage.py
kfserving/api/__init__.py
kfserving/api/creds_utils.py
kfserving/api/kf_serving_client.py
kfserving/api/kf_serving_watch.py
kfserving/constants/__init__.py
kfserving/constants/constants.py
kfserving/handlers/__init__.py
kfserving/handlers/http.py
kfserving/models/__init__.py
kfserving/models/knative_addressable.py
kfserving/models/knative_condition.py
kfserving/models/knative_status.py
kfserving/models/knative_url.py
kfserving/models/knative_volatile_time.py
kfserving/models/net_url_userinfo.py
kfserving/models/v1_time.py
kfserving/models/v1alpha1_model_spec.py
kfserving/models/v1alpha1_trained_model.py
kfserving/models/v1alpha1_trained_model_list.py
kfserving/models/v1alpha1_trained_model_spec.py
kfserving/models/v1alpha2_aix_explainer_spec.py
kfserving/models/v1alpha2_alibi_explainer_spec.py
kfserving/models/v1alpha2_batcher.py
kfserving/models/v1alpha2_custom_spec.py
kfserving/models/v1alpha2_deployment_spec.py
kfserving/models/v1alpha2_endpoint_spec.py
kfserving/models/v1alpha2_explainer_spec.py
kfserving/models/v1alpha2_inference_service.py
kfserving/models/v1alpha2_inference_service_list.py
kfserving/models/v1alpha2_inference_service_spec.py
kfserving/models/v1alpha2_inference_service_status.py
kfserving/models/v1alpha2_light_gbm_spec.py
kfserving/models/v1alpha2_logger.py
kfserving/models/v1alpha2_onnx_spec.py
kfserving/models/v1alpha2_pmml_spec.py
kfserving/models/v1alpha2_predictor_spec.py
kfserving/models/v1alpha2_py_torch_spec.py
kfserving/models/v1alpha2_sk_learn_spec.py
kfserving/models/v1alpha2_status_configuration_spec.py
kfserving/models/v1alpha2_tensorflow_spec.py
kfserving/models/v1alpha2_transformer_spec.py
kfserving/models/v1alpha2_triton_spec.py
kfserving/models/v1alpha2_xg_boost_spec.py
kfserving/models/v1beta1_aix_explainer_spec.py
kfserving-0.6.1.dist-info/METADATA
kfserving-0.6.1.dist-info/WHEEL
kfserving-0.6.1.dist-info/top_level.txt
kfserving-0.6.1.dist-info/RECORD
