Metadata-Version: 2.1
Name: kfserving
Version: 0.6.1
Summary: KFServing Python SDK
Home-page: https://github.com/kubeflow/kfserving/tree/master/python/kfserving
Author: Kubeflow Authors
Author-email: ellisbigelow@google.com, hejinchi@cn.ibm.com, dsun20@bloomberg.net
License: Apache License Version 2.0
Platform: UNKNOWN
Classifier: Intended Audience :: Developers
Classifier: Intended Audience :: Education
Classifier: Intended Audience :: Science/Research
Classifier: Programming Language :: Python :: 3
Classifier: Programming Language :: Python :: 3.6
Classifier: Programming Language :: Python :: 3.7
Classifier: License :: OSI Approved :: Apache Software License
Classifier: Operating System :: OS Independent
Classifier: Topic :: Scientific/Engineering
Classifier: Topic :: Scientific/Engineering :: Artificial Intelligence
Classifier: Topic :: Software Development
Classifier: Topic :: Software Development :: Libraries
Classifier: Topic :: Software Development :: Libraries :: Python Modules
Requires-Python: >=3.6
Requires-Dist: certifi (>=14.05.14)
Requires-Dist: six (>=1.15)
Requires-Dist: python-dateutil (>=2.5.3)
Requires-Dist: setuptools (>=21.0.0)
Requires-Dist: urllib3 (>=1.15.1)
Requires-Dist: kubernetes (>=12.0.0)
Requires-Dist: tornado (>=6.0.0)
Requires-Dist: argparse (>=1.4.0)
Requires-Dist: minio (<7.0.0,>=4.0.9)
Requires-Dist: google-cloud-storage (>=1.31.0)
Requires-Dist: adal (>=1.2.2)
Requires-Dist: table-logger (>=0.3.5)
Requires-Dist: numpy (>=1.17.3)
Requires-Dist: azure-storage-blob (<=2.1.0,>=1.3.0)
Requires-Dist: cloudevents (>=1.2.0)
Requires-Dist: avro (>=1.10.1)
Requires-Dist: boto3 (>=1.17.32)
Requires-Dist: botocore (>=1.20.32)
Requires-Dist: psutil (>=5.0)
Requires-Dist: ray[serve] (>=1.5.0)
Requires-Dist: grpcio (>=1.34.1)
Provides-Extra: test
Requires-Dist: pytest ; extra == 'test'
Requires-Dist: pytest-tornasync ; extra == 'test'
Requires-Dist: mypy ; extra == 'test'
